{
    "biolatency": [
        {
            "parse_plotter": "parse_histogram",
            "parse_function": "parse_histogram_output",
            "parse_function_args": [
                "(?P<usecs>\\[\\d+[A-Za-z]?(\\]|\\,\\s\\d+[A-Za-z]?\\)))\\s+(?P<count>\\d+)",
                "usecs",
                "count"
            ],
            "xlabel": "Time interval (usecs)"
        }
    ],
    "biolatency_interval": [
        {
            "parse_plotter": "parse_heatmap",
            "parse_function": "parse_histogram_output",
            "parse_function_args": [
                "(?P<usecs>\\[\\d+[A-Za-z]?(\\]|\\,\\s\\d+[A-Za-z]?\\)))\\s+(?P<count>\\d+)",
                "usecs",
                "count"
            ],
            "xlabel": "Time interval (usecs)"
        }
    ],
    "syscount": [
        {
            "parse_plotter": "parse_histogram",
            "parse_function": "parse_histogram_output",
            "parse_function_args": [
                "@syscall\\[(?P<syscall>.*)\\]:\\s+(?P<count>\\d+)",
                "syscall",
                "count",
                "@syscall",
                true,
                ["read","write","open","close","stat","fstat","lstat","poll","lseek","mmap","mprotect","munmap","brk","rt_sigaction","rt_sigprocmask","rt_sigreturn","ioctl","pread","pwrite","readv","writev","access","pipe","select","sched_yield","mremap","msync","mincore","madvise","shmget","shmat","shmctl","dup","dup2","pause","nanosleep","getitimer","alarm","setitimer","getpid","sendfile","socket","connect","accept","sendto","recvfrom","sendmsg","recvmsg","shutdown","bind","listen","getsockname","getpeername","socketpair","setsockopt","getsockopt","clone","fork","vfork","execve","exit","wait4","kill","uname","semget","semop","semctl","shmdt","msgget","msgsnd","msgrcv","msgctl","fcntl","flock","fsync","fdatasync","truncate","ftruncate","getdents","getcwd","chdir","fchdir","rename","mkdir","rmdir","creat","link","unlink","symlink","readlink","chmod","fchmod","chown","fchown","lchown","umask","gettimeofday","getrlimit","getrusage","sysinfo","times","ptrace","getuid","syslog","getgid","setuid","setgid","geteuid","getegid","setpgid","getppid","getpgrp","setsid","setreuid","setregid","getgroups","setgroups","setresuid","getresuid","setresgid","getresgid","getpgid","setfsuid","setfsgid","getsid","capget","capset","rt_sigpending","rt_sigtimedwait","rt_sigqueueinfo","rt_sigsuspend","sigaltstack","utime","mknod","uselib","personality","ustat","statfs","fstatfs","sysfs","getpriority","setpriority","sched_setparam","sched_getparam","sched_setscheduler","sched_getscheduler","sched_get_priority_max","sched_get_priority_min","sched_rr_get_interval","mlock","munlock","mlockall","munlockall","vhangup","modify_ldt","pivot_root","_sysctl","prctl","arch_prctl","adjtimex","setrlimit","chroot","sync","acct","settimeofday","mount","umount2","swapon","swapoff","reboot","sethostname","setdomainname","iopl","ioperm","create_module","init_module","delete_module","get_kernel_syms","query_module","quotactl","nfsservctl","getpmsg","putpmsg","afs_syscall","tuxcall","security","gettid","readahead","setxattr","lsetxattr","fsetxattr","getxattr","lgetxattr","fgetxattr","listxattr","llistxattr","flistxattr","removexattr","lremovexattr","fremovexattr","tkill","time","futex","sched_setaffinity","sched_getaffinity","set_thread_area","io_setup","io_destroy","io_getevents","io_submit","io_cancel","get_thread_area","lookup_dcookie","epoll_create","epoll_ctl_old","epoll_wait_old","remap_file_pages","getdents64","set_tid_address","restart_syscall","semtimedop","fadvise64","timer_create","timer_settime","timer_gettime","timer_getoverrun","timer_delete","clock_settime","clock_gettime","clock_getres","clock_nanosleep","exit_group","epoll_wait","epoll_ctl","tgkill","utimes","vserver","mbind","set_mempolicy","get_mempolicy","mq_open","mq_unlink","mq_timedsend","mq_timedreceive","mq_notify","mq_getsetattr","kexec_load","waitid","add_key","request_key","keyctl","ioprio_set","ioprio_get","inotify_init","inotify_add_watch","inotify_rm_watch","migrate_pages","openat","mkdirat","mknodat","fchownat","futimesat","newfstatat","unlinkat","renameat","linkat","symlinkat","readlinkat","fchmodat","faccessat","pselect6","ppoll","unshare","set_robust_list","get_robust_list","splice","tee","sync_file_range","vmsplice","move_pages","utimensat","epoll_pwait","signalfd","timerfd_create","eventfd","fallocate","timerfd_settime","timerfd_gettime","accept4","signalfd4","eventfd2","epoll_create1","dup3","pipe2","inotify_init1","preadv","pwritev","rt_tgsigqueueinfo","perf_event_open","recvmmsg","fanotify_init","fanotify_mark","prlimit64","name_to_handle_at","open_by_handle_at","clock_adjtime","syncfs","sendmmsg","setns","getcpu","process_vm_readv","process_vm_writev","kcmp","finit_module","sched_setattr","sched_getattr","renameat2","seccomp","getrandom","memfd_create","kexec_file_load","bpf","execveat","userfaultfd","membarrier","mlock2","copy_file_range","preadv2","pwritev2","pkey_mprotect","pkey_alloc","pkey_free","statx","io_pgetevents","rseq","pidfd_send_signal","io_uring_setup","io_uring_enter","io_uring_register","open_tree","move_mount","fsopen","fsconfig","fsmount","fspick","pidfd_open","clone3","close_range","openat2","pidfd_getfd","faccessat2","process_madvise","epoll_pwait2","mount_setattr","quotactl_fd","landlock_create_ruleset","landlock_add_rule","landlock_restrict_self","memfd_secret","process_mrelease","futex_waitv","set_mempolicy_home_node","cachestat"]
            ],
            "xlabel": "Syscall"
        },
        {
            "parse_plotter": "parse_histogram",
            "parse_function": "parse_histogram_output",
            "parse_function_args": [
                "@process\\[(?P<process>.*)\\]:\\s+(?P<count>\\d+)",
                "process",
                "count",
                "@process",
                true
            ],
            "xlabel": "Process"
        }
    ],
    "fsrwstat": [
        {
            "parse_plotter": "parse_time_series",
            "parse_function": "parse_fsrwstat_output",
            "parse_function_args": [[]],
            "xlabel": "Time"
        }
    ],
    "runqlat": [
        {
            "parse_plotter": "parse_histogram",
            "parse_function": "parse_histogram_output",
            "parse_function_args": [
                "(?P<usecs>\\[\\d+[A-Za-z]?(\\]|\\,\\s\\d+[A-Za-z]?\\)))\\s+(?P<count>\\d+)",
                "usecs",
                "count"
            ],
            "xlabel": "Time interval (usecs)"
        }
    ],
    "runqlat_interval": [
        {
            "parse_plotter": "parse_heatmap",
            "parse_function": "parse_histogram_output",
            "parse_function_args": [
                "(?P<usecs>\\[\\d+[A-Za-z]?(\\]|\\,\\s\\d+[A-Za-z]?\\)))\\s+(?P<count>\\d+)",
                "usecs",
                "count"
            ],
            "xlabel": "Time interval (usecs)"
        }
    ],
    "runqlen": [
        {
            "parse_plotter": "parse_histogram",
            "parse_function": "parse_histogram_output",
            "parse_function_args": [
                "(?P<length>\\[\\d+[A-Za-z]?(\\]|\\,\\s\\d+[A-Za-z]?\\)))\\s+(?P<count>\\d+)",
                "length",
                "count"
            ],
            "xlabel": "Run queue length"
        }
    ],
    "runqlen_interval": [
        {
            "parse_plotter": "parse_heatmap",
            "parse_function": "parse_histogram_output",
            "parse_function_args": [
                "(?P<length>\\[\\d+[A-Za-z]?(\\]|\\,\\s\\d+[A-Za-z]?\\)))\\s+(?P<count>\\d+)",
                "length",
                "count"
            ],
            "xlabel": "Run queue length"
        }
    ],
    "cpuwalk": [
        {
            "parse_plotter": "parse_histogram",
            "parse_function": "parse_histogram_output",
            "parse_function_args": [
                "(?P<cpu>\\[\\d+[A-Za-z]?(\\]|\\,\\s\\d+[A-Za-z]?\\)))\\s+(?P<count>\\d+)",
                "cpu",
                "count"
            ],
            "xlabel": "(C)PUs"
        }
    ],
    "cpuwalk_interval": [
        {
            "parse_plotter": "parse_heatmap",
            "parse_function": "parse_histogram_output",
            "parse_function_args": [
                "(?P<cpu>\\[\\d+[A-Za-z]?(\\]|\\,\\s\\d+[A-Za-z]?\\)))\\s+(?P<count>\\d+)",
                "cpu",
                "count"
            ],
            "xlabel": "(C)PUs"
        }
    ],
    "signals": [
        {
            "parse_plotter": "parse_clustered_stacked_bar",
            "parse_function": "parse_signals_output",
            "parse_function_args": [],
            "xlabel": "Command"
        }
    ],
    "vfscount": [
        {
            "parse_plotter": "parse_histogram",
            "parse_function": "parse_histogram_output",
            "parse_function_args": [
                "@\\[vfs_(?P<vfs>.*)\\]:\\s+(?P<count>\\d+)",
                "vfs",
                "count",
                "@",
                true
            ],
            "xlabel": "vfs function"
        }
    ],
    "vfssize": [
        {
            "parse_plotter": "parse_multiple_histogram",
            "parse_function": "parse_multiple_histogram_output",
            "parse_function_args": [
                "\\[(?P<name>[^,]*), (?P<type>[^]]*)\\]",
                "(?P<size>\\[\\d+[A-Za-z]?(\\]|\\,\\s\\d+[A-Za-z]?\\)))\\s+(?P<count>\\d+)",
                ["name", "type"],
                "vfs",
                "count"
            ],
            "xlabel": "Size (bytes)"
        }
    ],
    "vfssize_interval": [
        {
            "parse_plotter": "parse_multiple_heatmap",
            "parse_function": "parse_multiple_histogram_output",
            "parse_function_args": [
                "\\[(?P<name>[^,]*), (?P<type>[^]]*)\\]",
                "(?P<size>\\[\\d+[A-Za-z]?(\\]|\\,\\s\\d+[A-Za-z]?\\)))\\s+(?P<count>\\d+)",
                ["name", "type"],
                "vfs",
                "count"
            ],
            "xlabel": "Size (bytes)"
        }
    ],
    "ext4dist": [
        {
            "parse_plotter": "parse_multiple_histogram",
            "parse_function": "parse_ext4dist_output",
            "parse_function_args": [],
            "xlabel": "Time interval (usecs)"
        }
    ],
    "bitesize": [
        {
            "parse_plotter": "parse_multiple_histogram",
            "parse_function": "parse_bitesize_output",
            "parse_function_args": [],
            "xlabel": "Size (bytes)"
        }
    ],
    "netsize": [
        {
            "parse_plotter": "parse_multiple_histogram",
            "parse_function": "parse_netsize_output",
            "parse_function_args": [],
            "xlabel": "Size (bytes)"
        }
    ],
    "funccount": [
        {
            "parse_plotter": "parse_histogram",
            "parse_function": "parse_histogram_output",
            "parse_function_args": [
                "@functions\\[kprobe:(?P<function>.*)\\]:\\s+(?P<count>\\d+)",
                "function",
                "count",
                "@functions",
                true
            ],
            "xlabel": "Function"
        }
    ],
    "xfsdist": [
        {
            "parse_plotter": "parse_multiple_histogram",
            "parse_function": "parse_xfsdist_output",
            "parse_function_args": [],
            "xlabel": "Time interval (usecs)"
        }
    ],
    "xfsdist_interval": [
        {
            "parse_plotter": "parse_multiple_heatmap",
            "parse_function": "parse_multiple_histogram_output",
            "parse_function_args": [
                "\\[(?P<function>[^]]*)\\]",
                "(?P<usecs>\\[\\d+[A-Za-z]?(\\]|\\,\\s\\d+[A-Za-z]?\\)))\\s+(?P<count>\\d+)",
                ["function"],
                "usecs",
                "count"
            ],
            "xlabel": "Time interval (usecs)"
        }
    ],
    "pidpersec": [
        {
            "parse_plotter": "parse_time_series",
            "parse_function": "parse_pidpersec_output",
            "parse_function_args": [[]],
            "xlabel": "Time"
        }
    ],
    "ffaults": [
        {
            "parse_plotter": "parse_histogram",
            "parse_function": "parse_ffaults_output",
            "parse_function_args": [0],
            "xlabel": "Filename"
        }
    ],
    "hfaults": [
        {
            "parse_plotter": "parse_histogram",
            "parse_function": "parse_hfaults_output",
            "parse_function_args": [0],
            "xlabel": "Process"
        }
    ],
    "nettxlat": [
        {
            "parse_plotter": "parse_histogram",
            "parse_function": "parse_histogram_output",
            "parse_function_args": [
                "(?P<usecs>\\[\\d+[A-Za-z]?(\\]|\\,\\s\\d+[A-Za-z]?\\)))\\s+(?P<count>\\d+)",
                "usecs",
                "count"
            ],
            "xlabel": "Time interval (usecs)"
        }
    ],
    "socksize": [
        {
            "parse_plotter": "parse_multiple_histogram",
            "parse_function": "parse_socksize_output",
            "parse_function_args": [],
            "xlabel": "Size (bytes)"
        }
    ]
}
